pychamp/__init__.py
pychamp/configparser.py
pychamp/connection.py
pychamp/eda.py
pychamp/features_selection.py
pychamp/model.py
pychamp/net.py
pychamp/sampling.py
pychamp/stats.py
pychamp/viz.py
pychamp-1.1.0.dev4.dist-info/LICENSE.txt
pychamp-1.1.0.dev4.dist-info/METADATA
pychamp-1.1.0.dev4.dist-info/WHEEL
pychamp-1.1.0.dev4.dist-info/top_level.txt
pychamp-1.1.0.dev4.dist-info/RECORD
