Metadata-Version: 2.1
Name: pychamp
Version: 1.1.0.dev4
Summary: Data Science Tools
Home-page: https://github.com/paudelsagar/pychamp
Author: Sagar Paudel
Author-email: sagar.paudel18@gmail.com
License: UNKNOWN
Keywords: data science tools
Platform: UNKNOWN
Classifier: Programming Language :: Python :: 3
Classifier: License :: OSI Approved :: MIT License
Classifier: Operating System :: OS Independent
Requires-Python: >=3.6.7
Requires-Dist: wordcloud
Requires-Dist: seaborn
Requires-Dist: SQLAlchemy
Requires-Dist: statsmodels
Requires-Dist: graphviz
Requires-Dist: numpy
Requires-Dist: scipy
Requires-Dist: pandas
Requires-Dist: imbalanced-learn
Requires-Dist: matplotlib
Requires-Dist: pydotplus
Requires-Dist: ipython
Requires-Dist: imblearn
Requires-Dist: scikit-learn
